calculo_fatorial/__init__.py
calculo_fatorial/fatorial/__init__.py
calculo_fatorial/fatorial/fatorial_fab.py
calculo_fatorial/fatorial/file2_name.py
calculo_fatorial/module2_name/__init__.py
calculo_fatorial/module2_name/file1_name.py
calculo_fatorial/module2_name/file2_name.py
factorial_fab-0.0.1.dist-info/METADATA
factorial_fab-0.0.1.dist-info/WHEEL
factorial_fab-0.0.1.dist-info/top_level.txt
factorial_fab-0.0.1.dist-info/RECORD
