Metadata-Version: 2.1
Name: factorial-fab
Version: 0.0.1
Summary: Calculo fatorial utilizando o modulo fatorial da lib math
Home-page: https://github.com/fabricioeirim/package-template
Author: Fabricio
Author-email: fabricioeirim@gmail.com
Requires-Python: >=3.6
Requires-Dist: math
Requires-Dist: factorial
